{
  "code_artifact": "outputs/nsgrand_fir_smoke/artifacts/code_artifact.json",
  "experiment_name": "nsgrand_fir_smoke",
  "profile_to_id": {
    "A": 0,
    "C": 1
  },
  "profiles": [
    "A",
    "C"
  ],
  "splits": {
    "train": {
      "num_samples": 3000,
      "num_shards": 6,
      "shards": [
        {
          "backends": {
            "A": "SionnaTDLBackend",
            "C": "SionnaTDLBackend"
          },
          "num_samples": 500,
          "profiles": [
            "A",
            "C"
          ],
          "seed": 20260411,
          "shard_path": "outputs/nsgrand_fir_smoke/datasets/train/train_shard_0000.npz",
          "snr_max_db": 5.993199825286865,
          "snr_min_db": -1.9787441492080688,
          "summary_path": "outputs/nsgrand_fir_smoke/datasets/train/summaries/train_shard_0000.json"
        },
        {
          "backends": {
            "A": "SionnaTDLBackend",
            "C": "SionnaTDLBackend"
          },
          "num_samples": 500,
          "profiles": [
            "A",
            "C"
          ],
          "seed": 20260412,
          "shard_path": "outputs/nsgrand_fir_smoke/datasets/train/train_shard_0001.npz",
          "snr_max_db": 5.993602752685547,
          "snr_min_db": -1.9669320583343506,
          "summary_path": "outputs/nsgrand_fir_smoke/datasets/train/summaries/train_shard_0001.json"
        },
        {
          "backends": {
            "A": "SionnaTDLBackend",
            "C": "SionnaTDLBackend"
          },
          "num_samples": 500,
          "profiles": [
            "A",
            "C"
          ],
          "seed": 20260413,
          "shard_path": "outputs/nsgrand_fir_smoke/datasets/train/train_shard_0002.npz",
          "snr_max_db": 5.991517066955566,
          "snr_min_db": -1.9938006401062012,
          "summary_path": "outputs/nsgrand_fir_smoke/datasets/train/summaries/train_shard_0002.json"
        },
        {
          "backends": {
            "A": "SionnaTDLBackend",
            "C": "SionnaTDLBackend"
          },
          "num_samples": 500,
          "profiles": [
            "A",
            "C"
          ],
          "seed": 20260414,
          "shard_path": "outputs/nsgrand_fir_smoke/datasets/train/train_shard_0003.npz",
          "snr_max_db": 5.972661018371582,
          "snr_min_db": -1.9581776857376099,
          "summary_path": "outputs/nsgrand_fir_smoke/datasets/train/summaries/train_shard_0003.json"
        },
        {
          "backends": {
            "A": "SionnaTDLBackend",
            "C": "SionnaTDLBackend"
          },
          "num_samples": 500,
          "profiles": [
            "A",
            "C"
          ],
          "seed": 20260415,
          "shard_path": "outputs/nsgrand_fir_smoke/datasets/train/train_shard_0004.npz",
          "snr_max_db": 5.985861301422119,
          "snr_min_db": -1.998393177986145,
          "summary_path": "outputs/nsgrand_fir_smoke/datasets/train/summaries/train_shard_0004.json"
        },
        {
          "backends": {
            "A": "SionnaTDLBackend",
            "C": "SionnaTDLBackend"
          },
          "num_samples": 500,
          "profiles": [
            "A",
            "C"
          ],
          "seed": 20260416,
          "shard_path": "outputs/nsgrand_fir_smoke/datasets/train/train_shard_0005.npz",
          "snr_max_db": 5.98560094833374,
          "snr_min_db": -1.993985891342163,
          "summary_path": "outputs/nsgrand_fir_smoke/datasets/train/summaries/train_shard_0005.json"
        }
      ]
    },
    "val": {
      "num_samples": 800,
      "num_shards": 2,
      "shards": [
        {
          "backends": {
            "A": "SionnaTDLBackend",
            "C": "SionnaTDLBackend"
          },
          "num_samples": 500,
          "profiles": [
            "A",
            "C"
          ],
          "seed": 20261411,
          "shard_path": "outputs/nsgrand_fir_smoke/datasets/val/val_shard_0000.npz",
          "snr_max_db": 5.9973225593566895,
          "snr_min_db": -1.9992550611495972,
          "summary_path": "outputs/nsgrand_fir_smoke/datasets/val/summaries/val_shard_0000.json"
        },
        {
          "backends": {
            "A": "SionnaTDLBackend",
            "C": "SionnaTDLBackend"
          },
          "num_samples": 300,
          "profiles": [
            "A",
            "C"
          ],
          "seed": 20261412,
          "shard_path": "outputs/nsgrand_fir_smoke/datasets/val/val_shard_0001.npz",
          "snr_max_db": 5.999502658843994,
          "snr_min_db": -1.9903970956802368,
          "summary_path": "outputs/nsgrand_fir_smoke/datasets/val/summaries/val_shard_0001.json"
        }
      ]
    }
  }
}